webullsdkmdata/__init__.py
webullsdkmdata/common/__init__.py
webullsdkmdata/common/category.py
webullsdkmdata/common/direction.py
webullsdkmdata/common/exchange_code.py
webullsdkmdata/common/exercise_style.py
webullsdkmdata/common/expiration_cycle.py
webullsdkmdata/common/instrument_status.py
webullsdkmdata/common/option_type.py
webullsdkmdata/common/subscribe_type.py
webullsdkmdata/common/timespan.py
webullsdkmdata/quotes/__init__.py
webullsdkmdata/quotes/instrument.py
webullsdkmdata/quotes/market_data.py
webullsdkmdata/quotes/grpc/__init__.py
webullsdkmdata/quotes/grpc/instrument.py
webullsdkmdata/quotes/grpc/market_data.py
webullsdkmdata/quotes/grpc/response.py
webullsdkmdata/quotes/grpc/response_code.py
webullsdkmdata/quotes/grpc/pb/__init__.py
webullsdkmdata/quotes/grpc/pb/quote_pb2.py
webullsdkmdata/quotes/grpc/proto/__init__.py
webullsdkmdata/quotes/subscribe/__init__.py
webullsdkmdata/quotes/subscribe/ask_bid_result.py
webullsdkmdata/quotes/subscribe/basic_result.py
webullsdkmdata/quotes/subscribe/broker_result.py
webullsdkmdata/quotes/subscribe/default_client.py
webullsdkmdata/quotes/subscribe/message_pb2.py
webullsdkmdata/quotes/subscribe/order_result.py
webullsdkmdata/quotes/subscribe/payload_type.py
webullsdkmdata/quotes/subscribe/quote_decoder.py
webullsdkmdata/quotes/subscribe/quote_result.py
webullsdkmdata/quotes/subscribe/snapshot_decoder.py
webullsdkmdata/quotes/subscribe/snapshot_result.py
webullsdkmdata/quotes/subscribe/tick_decoder.py
webullsdkmdata/quotes/subscribe/tick_result.py
webullsdkmdata/request/__init__.py
webullsdkmdata/request/get_batch_historical_bars_request.py
webullsdkmdata/request/get_corp_action_request.py
webullsdkmdata/request/get_eod_bars_request.py
webullsdkmdata/request/get_historical_bars_request.py
webullsdkmdata/request/get_instruments_request.py
webullsdkmdata/request/get_snapshot_request.py
webullsdkmdata/request/grpc/__init__.py
webullsdkmdata/request/grpc/base_request.py
webull_python_sdk_mdata-0.1.18.dist-info/METADATA
webull_python_sdk_mdata-0.1.18.dist-info/WHEEL
webull_python_sdk_mdata-0.1.18.dist-info/top_level.txt
webull_python_sdk_mdata-0.1.18.dist-info/RECORD
