Metadata-Version: 2.4
Name: webull-python-sdk-mdata
Version: 0.1.18
Summary: The market data module of Webull Python SDK.
Home-page: 
Author: Webull
Author-email: 
License: Apache License 2.0
Platform: any
Requires-Dist: webull-python-sdk-core==0.1.18
Requires-Dist: webull-python-sdk-quotes-core==0.1.18
Dynamic: author
Dynamic: description-content-type
Dynamic: license
Dynamic: platform
Dynamic: requires-dist
Dynamic: summary
